vestige/__init__.py
vestige/__main__.py
vestige/constants.py
vestige/download_utils.py
vestige_cleaner-0.0.1a4.dist-info/METADATA
vestige_cleaner-0.0.1a4.dist-info/WHEEL
vestige_cleaner-0.0.1a4.dist-info/top_level.txt
vestige_cleaner-0.0.1a4.dist-info/RECORD
