Metadata-Version: 2.1
Name: vestige-cleaner
Version: 0.0.1a4
Summary: Remove commented code from projects automatically
Home-page: https://github.com/JamesDConley/Vestige
Author: James Conley
Author-email: jconley1+vestige@alumni.conncoll.edu
License: UNKNOWN
Platform: UNKNOWN
Classifier: Programming Language :: Python :: 3
Classifier: Operating System :: OS Independent
Requires-Python: >=3.6
Requires-Dist: bert-text-classifier
Requires-Dist: tqdm
Requires-Dist: comment-parser
Requires-Dist: argparse
Requires-Dist: numpy
